think_dashboard_agent/__init__.py
think_dashboard_agent/exceptions.py
think_dashboard_agent/main.py
think_dashboard_agent/providers/__init__.py
think_dashboard_agent/providers/base.py
think_dashboard_agent/providers/database.py
think_dashboard_agent/providers/elasticsearch.py
think_dashboard_agent/providers/redis_provider.py
think_dashboard_agent/providers/ssl_provider.py
think_dashboard_agent/responses.py
think_dashboard_agent/types.py
think_dashboard_agent-1.0.8.dist-info/WHEEL
think_dashboard_agent-1.0.8.dist-info/METADATA
think_dashboard_agent-1.0.8.dist-info/RECORD
