Metadata-Version: 2.1
Name: think-dashboard-agent
Version: 1.0.8
Summary: 
Author: Suhrob Malikov
Author-email: suhrob@thinkland.uz
Requires-Python: >=3.6,<4.0
Classifier: Programming Language :: Python :: 3
Classifier: Programming Language :: Python :: 3.10
Classifier: Programming Language :: Python :: 3.6
Classifier: Programming Language :: Python :: 3.7
Classifier: Programming Language :: Python :: 3.8
Classifier: Programming Language :: Python :: 3.9
Requires-Dist: APScheduler (>=3.9.1,<4.0.0)
Requires-Dist: psycopg2-binary (>=2.9.3,<3.0.0)
Requires-Dist: pydantic (>=1.9.1,<2.0.0)
Requires-Dist: redis (>=4.3.4,<5.0.0)
Requires-Dist: requests (>=2.28.1,<3.0.0)
Requires-Dist: toml (>=0.10.2,<0.11.0)
